subtil/__init__.py
subtil/data.py
subtil/database.py
subtil/datamining.py
subtil/modeltree.py
subtil/plotting.py
subtil/subtildb-structure-sqlite.sql
subtil/utils.py
subtil-0.1.0.dist-info/LICENSE.txt
subtil-0.1.0.dist-info/METADATA
subtil-0.1.0.dist-info/RECORD
subtil-0.1.0.dist-info/WHEEL
subtil-0.1.0.dist-info/top_level.txt
