Metadata-Version: 2.1
Name: subtil
Version: 0.1.0
Summary: Subgroup discovery platform for examination of Bacterial TIme-Lapse microscopy dataset
Home-page: https://dtai.cs.kuleuven.be/software/python-subtle/
Author: Antoine Adam
Author-email: antoine.adam@cs.kuleuven.be
License: MIT
Project-URL: Source, https://github.com/AntoineAdam/subtil
Project-URL: Documentation, https://dtai.cs.kuleuven.be/software/python-subtle/
Project-URL: Tracker, https://github.com/AntoineAdam/subtil/issues
Keywords: time-lapse-microsopy subgroup-discovery microbiology
Platform: UNKNOWN
Classifier: Development Status :: 4 - Beta
Classifier: Intended Audience :: Science/Research
Classifier: Topic :: Scientific/Engineering :: Bio-Informatics
Classifier: License :: OSI Approved :: MIT License
Classifier: Programming Language :: Python :: 2
Classifier: Programming Language :: Python :: 2.7
Requires-Python: >=2.7, <3
Requires-Dist: numpy
Requires-Dist: scipy
Requires-Dist: matplotlib
Requires-Dist: scikit-learn
